imnn_tf/__init__.py
imnn_tf/imnn.py
imnn_tf/lfi/LFI.py
imnn_tf/lfi/__init__.py
imnn_tf/utils/TFRecords.py
imnn_tf/utils/__init__.py
imnn_tf/utils/utils.py
imnn_tf-0.2.0.dist-info/LICENSE
imnn_tf-0.2.0.dist-info/METADATA
imnn_tf-0.2.0.dist-info/WHEEL
imnn_tf-0.2.0.dist-info/top_level.txt
imnn_tf-0.2.0.dist-info/RECORD
