Metadata-Version: 2.1
Name: imnn-tf
Version: 0.2.0
Summary: Using neural networks to extract sufficient statistics from         data by maximising the Fisher information
Home-page: https://bitbucket.org/tomcharnock/imnn-tf
Author: Tom Charnock
Author-email: tom@charnock.fr
License: UNKNOWN
Platform: UNKNOWN
Classifier: Programming Language :: Python :: 3.7
Classifier: License :: OSI Approved :: MIT License
Classifier: Operating System :: OS Independent
Requires-Python: >=3
Requires-Dist: tensorflow (>=2.1.0)
Requires-Dist: tqdm (>=4.31.0)
Requires-Dist: numpy (>=1.16.0)
Requires-Dist: scipy (>=1.4.1)
Requires-Dist: matplotlib
